akoma2md-2.0.21.dist-info/licenses/LICENSE
normattiva2md/__init__.py
normattiva2md/akoma_utils.py
normattiva2md/cli.py
normattiva2md/constants.py
normattiva2md/exa_api.py
normattiva2md/markdown_converter.py
normattiva2md/multi_document.py
normattiva2md/normattiva_api.py
normattiva2md/utils.py
normattiva2md/xml_parser.py
akoma2md-2.0.21.dist-info/METADATA
akoma2md-2.0.21.dist-info/WHEEL
akoma2md-2.0.21.dist-info/entry_points.txt
akoma2md-2.0.21.dist-info/top_level.txt
akoma2md-2.0.21.dist-info/RECORD
